fortlab/__init__.py
fortlab/__main__.py
fortlab/kgextra.py
fortlab/kggenfile.py
fortlab/kgplugin.py
fortlab/kgutils.py
fortlab/main.py
fortlab/kernel/__init__.py
fortlab/kernel/kernelgen.py
fortlab/kernel/plugins/__init__.py
fortlab/kernel/plugins/coverage/__init__.py
fortlab/kernel/plugins/coverage/gen_coverage_files.py
fortlab/kernel/plugins/debug/__init__.py
fortlab/kernel/plugins/debug/debug_add_sum.py
fortlab/kernel/plugins/gencore/__init__.py
fortlab/kernel/plugins/gencore/gen_driver.py
fortlab/kernel/plugins/gencore/gen_kernel_callsite_file.py
fortlab/kernel/plugins/gencore/gen_kernel_files.py
fortlab/kernel/plugins/gencore/gen_state_callsite_file.py
fortlab/kernel/plugins/gencore/gen_type.py
fortlab/kernel/plugins/gencore/gen_typedecl_in_module.py
fortlab/kernel/plugins/gencore/gen_typedecl_in_parentblock.py
fortlab/kernel/plugins/gencore/gen_typedecl_in_type.py
fortlab/kernel/plugins/gencore/gen_write_in_module.py
fortlab/kernel/plugins/gencore/gencore_subr.py
fortlab/kernel/plugins/gencore/gencore_utils.py
fortlab/kernel/plugins/perturb/__init__.py
fortlab/kernel/plugins/perturb/perturb_kernel_callsite_file.py
fortlab/kernel/plugins/simple_timing/__init__.py
fortlab/kernel/plugins/simple_timing/simple_timing.py
fortlab/kernel/plugins/verification/__init__.py
fortlab/kernel/plugins/verification/verify_callsite_file.py
fortlab/kernel/plugins/verification/verify_subr.py
fortlab/kernel/plugins/verification/verify_type.py
fortlab/kernel/plugins/verification/verify_typedecl_in_module.py
fortlab/kernel/plugins/verification/verify_typedecl_in_parentblock.py
fortlab/kernel/plugins/verification/verify_utils.py
fortlab/resolver/Fortran2003.py
fortlab/resolver/__init__.py
fortlab/resolver/api.py
fortlab/resolver/base_classes.py
fortlab/resolver/block_statements.py
fortlab/resolver/kganalyze.py
fortlab/resolver/kgintrinsics.py
fortlab/resolver/kgparse.py
fortlab/resolver/kgsearch.py
fortlab/resolver/main.py
fortlab/resolver/parsefortran.py
fortlab-1.1.5.dist-info/LICENSE
fortlab-1.1.5.dist-info/METADATA
fortlab-1.1.5.dist-info/WHEEL
fortlab-1.1.5.dist-info/entry_points.txt
fortlab-1.1.5.dist-info/top_level.txt
fortlab-1.1.5.dist-info/RECORD
